[
    {
        "Names": "Joao",
        "AnniversaryDate": "2012/10/10",
        "AnniversaryType": "birthday",
        "Description": "My 21y birthday!",
        "Email": "johnarmques.br200@Gmail.com",
        "PhoneNumber": "15196154641",
        "Address": {
            "StreetAddress": "80 Speers Road",
            "Municipality": "Oakville",
            "Province": "ON",
            "PostalCode": "L6H 3H5"
        }
    },
    {
        "Names": "Gui",
        "AnniversaryDate": "2012/10/10",
        "AnniversaryType": "birthday",
        "Description": "My 24th birthday!",
        "Email": "gui@gmail.com",
        "PhoneNumber": "15196154641",
        "Address": {
            "StreetAddress": "1130 Albert Street",
            "Municipality": "London",
            "Province": "ON",
            "PostalCode": "N5W 5K6"
        }
    },
    {
        "Names": "Pedro",
        "AnniversaryDate": "2053/10/15",
        "AnniversaryType": "birthday",
        "Description": "lastBirthday",
        "Email": "ped@ex.ca",
        "PhoneNumber": "15196154843",
        "Address": {
            "StreetAddress": "110 Oxford",
            "Municipality": "London",
            "Province": "ON",
            "PostalCode": "N6H 1R5"
        }
    },
    {
        "Names": "Manny",
        "AnniversaryDate": "2012/12/12",
        "AnniversaryType": "death",
        "Description": "ded",
        "Email": "manny@gmail.com",
        "PhoneNumber": "",
        "Address": {
            "StreetAddress": "",
            "Municipality": "",
            "Province": "ON",
            "PostalCode": "N6K 3F5"
        }
    }
]